upagerduty/__init__.py
upagerduty/command.py
upagerduty/version.py
upagerduty-0.4.2.dist-info/METADATA
upagerduty-0.4.2.dist-info/WHEEL
upagerduty-0.4.2.dist-info/entry_points.txt
upagerduty-0.4.2.dist-info/licenses/LICENSE
upagerduty-0.4.2.dist-info/RECORD
