Metadata-Version: 2.3
Name: upagerduty
Version: 0.4.2
Summary: Library for the PagerDuty service API
Project-URL: Homepage, http://github.com/mrmeszaros/upagerduty
Author-email: Mészáros Máté Róbert <mateusz.meszaros@gmail.com>, Samuel Stauffer <samuel@playhaven.com>
License: Copyright 2010 Samuel Stauffer
License-File: LICENSE
Classifier: Development Status :: 4 - Beta
Classifier: Environment :: Console
Classifier: Intended Audience :: Developers
Classifier: License :: OSI Approved :: BSD License
Classifier: Operating System :: OS Independent
Classifier: Programming Language :: Python
Classifier: Programming Language :: Python :: 3
Classifier: Topic :: Software Development
Classifier: Topic :: Software Development :: Libraries
Classifier: Topic :: Software Development :: Libraries :: Python Modules
